{
    "version": "https://jsonfeed.org/version/1",
    "title": "welcome to my world • All posts by \"概念介绍\" tag",
    "description": "",
    "home_page_url": "http://example.com",
    "items": [
        {
            "id": "http://example.com/2023/10/27/%E9%9B%86%E5%90%88/",
            "url": "http://example.com/2023/10/27/%E9%9B%86%E5%90%88/",
            "title": "集合",
            "date_published": "2023-10-27T07:28:25.000Z",
            "content_html": "<h1 id=\"新概念-集合\"><a class=\"markdownIt-Anchor\" href=\"#新概念-集合\">#</a> 新概念 - 集合</h1>\n<p>集合是可变的数组（嗯，在我看来可以这样子认为）。不过它不能装基础数据类型</p>\n<p>以下是集合的一些基本操作，增删改查</p>\n<figure class=\"highlight java\"><table><tr><td class=\"gutter\"><pre><span class=\"line\">1</span><br><span class=\"line\">2</span><br><span class=\"line\">3</span><br><span class=\"line\">4</span><br><span class=\"line\">5</span><br><span class=\"line\">6</span><br><span class=\"line\">7</span><br><span class=\"line\">8</span><br><span class=\"line\">9</span><br><span class=\"line\">10</span><br><span class=\"line\">11</span><br><span class=\"line\">12</span><br><span class=\"line\">13</span><br><span class=\"line\">14</span><br><span class=\"line\">15</span><br><span class=\"line\">16</span><br><span class=\"line\">17</span><br><span class=\"line\">18</span><br><span class=\"line\">19</span><br><span class=\"line\">20</span><br><span class=\"line\">21</span><br><span class=\"line\">22</span><br><span class=\"line\">23</span><br><span class=\"line\">24</span><br><span class=\"line\">25</span><br><span class=\"line\">26</span><br><span class=\"line\">27</span><br></pre></td><td class=\"code\"><pre><span class=\"line\"><span class=\"keyword\">import</span> java.util.ArrayList;</span><br><span class=\"line\"></span><br><span class=\"line\"><span class=\"keyword\">public</span> <span class=\"keyword\">class</span> <span class=\"title class_\">demol1_jihe</span> &#123;</span><br><span class=\"line\">    <span class=\"keyword\">public</span> <span class=\"keyword\">static</span> <span class=\"keyword\">void</span> <span class=\"title function_\">main</span><span class=\"params\">(String[] args)</span> &#123;</span><br><span class=\"line\">        ArrayList&lt;String&gt; s=<span class=\"keyword\">new</span> <span class=\"title class_\">ArrayList</span>&lt;&gt;();</span><br><span class=\"line\">        s.add(<span class=\"string\">&quot;aaa&quot;</span>);</span><br><span class=\"line\">        System.out.println(s);</span><br><span class=\"line\">        s.add(<span class=\"string\">&quot;aaa&quot;</span>);</span><br><span class=\"line\">        s.add(<span class=\"string\">&quot;bbb&quot;</span>);</span><br><span class=\"line\">        s.add(<span class=\"string\">&quot;ddd&quot;</span>);</span><br><span class=\"line\">        System.out.println(s);</span><br><span class=\"line\">        <span class=\"comment\">//删除</span></span><br><span class=\"line\">        s.remove(<span class=\"number\">0</span>);</span><br><span class=\"line\">        System.out.println(s);</span><br><span class=\"line\">        s.remove(<span class=\"string\">&quot;aaa&quot;</span>);</span><br><span class=\"line\">        System.out.println(s);</span><br><span class=\"line\">        <span class=\"comment\">//改</span></span><br><span class=\"line\">        s.set(<span class=\"number\">0</span>,<span class=\"string\">&quot;lll&quot;</span>);</span><br><span class=\"line\">        System.out.println(s);</span><br><span class=\"line\">        System.out.println(s.get(<span class=\"number\">0</span>));</span><br><span class=\"line\">        <span class=\"keyword\">for</span> (<span class=\"type\">int</span> <span class=\"variable\">i</span> <span class=\"operator\">=</span> <span class=\"number\">0</span>; i &lt; s.size(); i++) &#123;</span><br><span class=\"line\">            String s1=s.get(i);</span><br><span class=\"line\">            System.out.println(s1);</span><br><span class=\"line\">        &#125;</span><br><span class=\"line\">    &#125;</span><br><span class=\"line\">&#125;</span><br><span class=\"line\"></span><br></pre></td></tr></table></figure>\n",
            "tags": [
                "概念介绍"
            ]
        }
    ]
}